cs_dynamicpages/__init__.py
cs_dynamicpages/configure.zcml
cs_dynamicpages/dependencies.zcml
cs_dynamicpages/interfaces.py
cs_dynamicpages/permissions.zcml
cs_dynamicpages/profiles.zcml
cs_dynamicpages/testing.py
cs_dynamicpages/utils.py
cs_dynamicpages/behaviors/__init__.py
cs_dynamicpages/behaviors/configure.zcml
cs_dynamicpages/behaviors/configure.zcml.example
cs_dynamicpages/behaviors/extra_class.py
cs_dynamicpages/behaviors/fetchpriority_image.py
cs_dynamicpages/behaviors/link_info.py
cs_dynamicpages/behaviors/related_image.py
cs_dynamicpages/behaviors/row_columns.py
cs_dynamicpages/behaviors/row_vertical_spacing.py
cs_dynamicpages/behaviors/row_width.py
cs_dynamicpages/browser/__init__.py
cs_dynamicpages/browser/body_class.py
cs_dynamicpages/browser/configure.zcml
cs_dynamicpages/browser/static/.gitkeep
cs_dynamicpages/browser/static/delete-row.js
cs_dynamicpages/browser/static/dynamicpageview.css
cs_dynamicpages/browser/static/edit_dynamicpagerow.js
cs_dynamicpages/browser/static/editmode-toggle.js
cs_dynamicpages/browser/static/reorder-rows.js
cs_dynamicpages/browser/static/toast-handler.js
cs_dynamicpages/content/__init__.py
cs_dynamicpages/content/dynamic_page_folder.py
cs_dynamicpages/content/dynamic_page_folder.xml
cs_dynamicpages/content/dynamic_page_row.py
cs_dynamicpages/content/dynamic_page_row.xml
cs_dynamicpages/content/dynamic_page_row_featured.py
cs_dynamicpages/content/dynamic_page_row_featured.xml
cs_dynamicpages/controlpanels/__init__.py
cs_dynamicpages/controlpanels/configure.zcml
cs_dynamicpages/controlpanels/dynamic_pages_control_panel/__init__.py
cs_dynamicpages/controlpanels/dynamic_pages_control_panel/configure.zcml
cs_dynamicpages/controlpanels/dynamic_pages_control_panel/controlpanel.py
cs_dynamicpages/indexers/__init__.py
cs_dynamicpages/indexers/configure.zcml
cs_dynamicpages/indexers/content_index_extender.py
cs_dynamicpages/locales/__init__.py
cs_dynamicpages/locales/__main__.py
cs_dynamicpages/locales/cs_dynamicpages.pot
cs_dynamicpages-1.0.0b4.dist-info/METADATA
cs_dynamicpages-1.0.0b4.dist-info/WHEEL
cs_dynamicpages-1.0.0b4.dist-info/entry_points.txt
cs_dynamicpages-1.0.0b4.dist-info/licenses/LICENSE.GPL
cs_dynamicpages-1.0.0b4.dist-info/licenses/LICENSE.md
cs_dynamicpages-1.0.0b4.dist-info/RECORD
