Metadata-Version: 2.4
Name: cs_dynamicpages
Version: 1.0.0b4
Summary: A new addon for Plone
Project-URL: Homepage, https://github.com/codesyntax/cs_dynamicpages
Project-URL: PyPI, https://pypi.org/project/cs_dynamicpages
Project-URL: Source, https://github.com/codesyntax/cs_dynamicpages
Project-URL: Tracker, https://github.com/codesyntax/cs_dynamicpages/issues
Author-email: CodeSyntax <plone@codesyntax.com>
License-File: LICENSE.GPL
License-File: LICENSE.md
Keywords: CMS,Plone,Python
Classifier: Development Status :: 3 - Alpha
Classifier: Environment :: Web Environment
Classifier: Framework :: Plone
Classifier: Framework :: Plone :: 6.0
Classifier: Framework :: Plone :: 6.1
Classifier: Framework :: Plone :: Addon
Classifier: License :: OSI Approved :: GNU General Public License v2 (GPLv2)
Classifier: Operating System :: OS Independent
Classifier: Programming Language :: Python
Classifier: Programming Language :: Python :: 3.10
Classifier: Programming Language :: Python :: 3.11
Classifier: Programming Language :: Python :: 3.12
Classifier: Programming Language :: Python :: 3.13
Requires-Python: <3.14,>=3.10
Requires-Dist: collective-z3cform-datagridfield
Requires-Dist: plone-api
Requires-Dist: plone-app-upgrade
Requires-Dist: products-cmfplone
Provides-Extra: release
Requires-Dist: zest-pocompile; extra == 'release'
Requires-Dist: zest-releaser[recommended]; extra == 'release'
Requires-Dist: zestreleaser-towncrier; extra == 'release'
Provides-Extra: test
Requires-Dist: horse-with-no-namespace; extra == 'test'
Requires-Dist: plone-app-contenttypes[test]; extra == 'test'
Requires-Dist: plone-app-testing; extra == 'test'
Requires-Dist: plone-classicui; extra == 'test'
Requires-Dist: plone-restapi[test]; extra == 'test'
Requires-Dist: pytest; extra == 'test'
Requires-Dist: pytest-cov; extra == 'test'
Requires-Dist: pytest-plone>=0.5.0; extra == 'test'
